multical/__init__.py
multical/camera.py
multical/camera_fisheye.py
multical/display.py
multical/graph.py
multical/tables.py
multical/threading.py
multical/workspace.py
multical/app/__init__.py
multical/app/boards.py
multical/app/calibrate.py
multical/app/intrinsic.py
multical/app/multical.py
multical/app/vis.py
multical/board/__init__.py
multical/board/aprilgrid.py
multical/board/aprilgrid_detector.py
multical/board/board.py
multical/board/calico_config.py
multical/board/charuco.py
multical/board/common.py
multical/config/__init__.py
multical/config/arguments.py
multical/config/runtime.py
multical/config/workspace.py
multical/image/__init__.py
multical/image/detect.py
multical/image/display.py
multical/image/find.py
multical/interface/__init__.py
multical/interface/camera.ui
multical/interface/camera_params.py
multical/interface/layout.py
multical/interface/ui_files.py
multical/interface/view_table.py
multical/interface/viewer_image.py
multical/interface/visualizer.py
multical/interface/visualizer.ui
multical/interface/viewer_3d/marker.py
multical/interface/viewer_3d/moving_board.py
multical/interface/viewer_3d/moving_cameras.py
multical/interface/viewer_3d/viewer_3d.py
multical/interface/viewer_3d/vtk_tools.py
multical/io/__init__.py
multical/io/detections.py
multical/io/export_calib.py
multical/io/import_calib.py
multical/io/logging.py
multical/io/pprint.py
multical/io/report.py
multical/motion/__init__.py
multical/motion/hand_eye.py
multical/motion/motion_model.py
multical/motion/rolling_frames.py
multical/motion/static_frames.py
multical/optimization/__init__.py
multical/optimization/calibration.py
multical/optimization/hand_eye.py
multical/optimization/parameters.py
multical/optimization/pose_set.py
multical/transform/common.py
multical/transform/hand_eye.py
multical/transform/hypothesis.py
multical/transform/interpolate.py
multical/transform/matrix.py
multical/transform/qtvec.py
multical/transform/rtvec.py
multical/transform/smooth_6d.py
multical-0.2.1.dist-info/LICENSE
multical-0.2.1.dist-info/METADATA
multical-0.2.1.dist-info/WHEEL
multical-0.2.1.dist-info/entry_points.txt
multical-0.2.1.dist-info/top_level.txt
multical-0.2.1.dist-info/RECORD
