Metadata-Version: 2.1
Name: multical
Version: 0.2.1
Summary: Flexible multi-camera multi-board camera calibration library and application.
Home-page: https://github.com/saulzar/multical
Author: Oliver Batchelor
Author-email: saulzar@gmail.com
License: UNKNOWN
Platform: UNKNOWN
Classifier: Programming Language :: Python :: 3
Classifier: License :: OSI Approved :: GNU Lesser General Public License v3 (LGPLv3)
Classifier: Operating System :: OS Independent
Classifier: Topic :: Multimedia :: Graphics
Classifier: Topic :: Scientific/Engineering :: Image Processing
Classifier: Topic :: Multimedia :: Graphics :: Capture :: Digital Camera
Requires-Python: >=3.6
License-File: LICENSE
Requires-Dist: numpy
Requires-Dist: numba
Requires-Dist: scipy
Requires-Dist: matplotlib
Requires-Dist: opencv-contrib-python (>=4.5.0.0)
Requires-Dist: simple-parsing
Requires-Dist: natsort
Requires-Dist: cached-property
Requires-Dist: py-structs (>=0.2.7)
Requires-Dist: palettable
Requires-Dist: numpy-quaternion
Requires-Dist: omegaconf
Requires-Dist: packaging
Requires-Dist: tqdm
Provides-Extra: interactive
Requires-Dist: matplotlib ; extra == 'interactive'
Requires-Dist: qtpy ; extra == 'interactive'
Requires-Dist: pyvistaqt ; extra == 'interactive'
Requires-Dist: pyvista ; extra == 'interactive'
Requires-Dist: colour ; extra == 'interactive'
Requires-Dist: qtawesome ; extra == 'interactive'
